[{"id":1,"first_name":"Andriana","last_name":"Jurisch","avatar":"https://robohash.org/repudiandaequirem.png?size=50x50&set=set1"},
{"id":2,"first_name":"Ruben","last_name":"Benez","avatar":"https://robohash.org/repudiandaevitaeillum.png?size=50x50&set=set1"},
{"id":3,"first_name":"Leroy","last_name":"Clappson","avatar":"https://robohash.org/quisrationenemo.png?size=50x50&set=set1"},
{"id":4,"first_name":"Solly","last_name":"McColl","avatar":"https://robohash.org/doloresquamvoluptatem.bmp?size=50x50&set=set1"},
{"id":5,"first_name":"King","last_name":"Mackison","avatar":"https://robohash.org/animidolorepossimus.png?size=50x50&set=set1"},
{"id":6,"first_name":"Anna-diane","last_name":"Garnul","avatar":"https://robohash.org/eiusomnisnihil.png?size=50x50&set=set1"},
{"id":7,"first_name":"Nicolis","last_name":"Mottini","avatar":"https://robohash.org/facilisinciduntvoluptatum.bmp?size=50x50&set=set1"},
{"id":8,"first_name":"Ignace","last_name":"McCorley","avatar":"https://robohash.org/natusinventoreullam.bmp?size=50x50&set=set1"},
{"id":9,"first_name":"Lexine","last_name":"Muselli","avatar":"https://robohash.org/repudiandaequisvoluptas.jpg?size=50x50&set=set1"},
{"id":10,"first_name":"Darill","last_name":"Tassell","avatar":"https://robohash.org/voluptascumquevoluptatem.png?size=50x50&set=set1"},
{"id":11,"first_name":"Hew","last_name":"Thornton","avatar":"https://robohash.org/voluptatedebitismagnam.png?size=50x50&set=set1"},
{"id":12,"first_name":"Stanford","last_name":"McLeese","avatar":"https://robohash.org/quamrepudiandaeexplicabo.png?size=50x50&set=set1"},
{"id":13,"first_name":"Kay","last_name":"Allom","avatar":"https://robohash.org/sedoccaecativoluptatem.bmp?size=50x50&set=set1"},
{"id":14,"first_name":"Danyelle","last_name":"Carletti","avatar":"https://robohash.org/enimautut.bmp?size=50x50&set=set1"},
{"id":15,"first_name":"Deirdre","last_name":"Parslow","avatar":"https://robohash.org/blanditiisutqui.png?size=50x50&set=set1"},
{"id":16,"first_name":"Ernesto","last_name":"Crossby","avatar":"https://robohash.org/harumrepellatdeleniti.bmp?size=50x50&set=set1"},
{"id":17,"first_name":"Catharine","last_name":"Dinis","avatar":"https://robohash.org/errorquopariatur.bmp?size=50x50&set=set1"},
{"id":18,"first_name":"Laverna","last_name":"Strewthers","avatar":"https://robohash.org/quasnatusrepellat.jpg?size=50x50&set=set1"},
{"id":19,"first_name":"Arney","last_name":"Birden","avatar":"https://robohash.org/sedtemporibusmaxime.png?size=50x50&set=set1"},
{"id":20,"first_name":"Dominic","last_name":"Boast","avatar":"https://robohash.org/aliasquiaautem.png?size=50x50&set=set1"},
{"id":21,"first_name":"Urban","last_name":"Preece","avatar":"https://robohash.org/minimasitillo.jpg?size=50x50&set=set1"},
{"id":22,"first_name":"Adel","last_name":"Kopec","avatar":"https://robohash.org/corporismagnamlaborum.bmp?size=50x50&set=set1"},
{"id":23,"first_name":"Zondra","last_name":"Schirok","avatar":"https://robohash.org/numquamvoluptatumblanditiis.jpg?size=50x50&set=set1"},
{"id":24,"first_name":"Quincy","last_name":"Laviss","avatar":"https://robohash.org/inconsequatursunt.png?size=50x50&set=set1"},
{"id":25,"first_name":"Hilarius","last_name":"Ladloe","avatar":"https://robohash.org/quiavoluptassint.png?size=50x50&set=set1"},
{"id":26,"first_name":"Keene","last_name":"Lindsley","avatar":"https://robohash.org/utcommoditempore.png?size=50x50&set=set1"},
{"id":27,"first_name":"Katine","last_name":"Brangan","avatar":"https://robohash.org/quidemconsequaturblanditiis.jpg?size=50x50&set=set1"},
{"id":28,"first_name":"Thia","last_name":"Rouf","avatar":"https://robohash.org/excepturiidnihil.bmp?size=50x50&set=set1"},
{"id":29,"first_name":"Ophelie","last_name":"Delcastel","avatar":"https://robohash.org/hicconsecteturmollitia.png?size=50x50&set=set1"},
{"id":30,"first_name":"Leanna","last_name":"Adamski","avatar":"https://robohash.org/autemnisiodio.jpg?size=50x50&set=set1"},
{"id":31,"first_name":"Kenna","last_name":"Feaveer","avatar":"https://robohash.org/autipsadolorem.bmp?size=50x50&set=set1"},
{"id":32,"first_name":"Sutherlan","last_name":"Quaintance","avatar":"https://robohash.org/quiquiaperferendis.bmp?size=50x50&set=set1"},
{"id":33,"first_name":"Horace","last_name":"Logg","avatar":"https://robohash.org/etutfacilis.jpg?size=50x50&set=set1"},
{"id":34,"first_name":"Raeann","last_name":"Jankovsky","avatar":"https://robohash.org/autemvoluptasmollitia.png?size=50x50&set=set1"},
{"id":35,"first_name":"Vally","last_name":"Hartop","avatar":"https://robohash.org/optiosequivoluptatibus.png?size=50x50&set=set1"},
{"id":36,"first_name":"Maia","last_name":"Rawles","avatar":"https://robohash.org/estquosassumenda.png?size=50x50&set=set1"},
{"id":37,"first_name":"Wylma","last_name":"Antoniottii","avatar":"https://robohash.org/exmaioresquis.jpg?size=50x50&set=set1"},
{"id":38,"first_name":"Hyacinthie","last_name":"Rozenzweig","avatar":"https://robohash.org/autempraesentiumeum.png?size=50x50&set=set1"},
{"id":39,"first_name":"Hank","last_name":"Khristoforov","avatar":"https://robohash.org/possimusrepellendusaut.png?size=50x50&set=set1"},
{"id":40,"first_name":"Zea","last_name":"Robecon","avatar":"https://robohash.org/repudiandaeeumaut.bmp?size=50x50&set=set1"},
{"id":41,"first_name":"Seline","last_name":"Baraja","avatar":"https://robohash.org/veritatisomnisaccusantium.png?size=50x50&set=set1"},
{"id":42,"first_name":"Doy","last_name":"Stearnes","avatar":"https://robohash.org/maximesuntenim.jpg?size=50x50&set=set1"},
{"id":43,"first_name":"Aurel","last_name":"Vasyukhnov","avatar":"https://robohash.org/quiavoluptassit.png?size=50x50&set=set1"},
{"id":44,"first_name":"Cob","last_name":"Seckington","avatar":"https://robohash.org/distinctiorepudiandaecumque.png?size=50x50&set=set1"},
{"id":45,"first_name":"Rocky","last_name":"McKendo","avatar":"https://robohash.org/rationesintconsectetur.bmp?size=50x50&set=set1"},
{"id":46,"first_name":"Callida","last_name":"Shuter","avatar":"https://robohash.org/saepequimolestiae.png?size=50x50&set=set1"},
{"id":47,"first_name":"Thatcher","last_name":"Patek","avatar":"https://robohash.org/voluptatemnatusvoluptatem.bmp?size=50x50&set=set1"},
{"id":48,"first_name":"Mina","last_name":"Zorener","avatar":"https://robohash.org/odionecessitatibusconsequatur.jpg?size=50x50&set=set1"},
{"id":49,"first_name":"Hamel","last_name":"Swaite","avatar":"https://robohash.org/etducimusdebitis.bmp?size=50x50&set=set1"},
{"id":50,"first_name":"Karrie","last_name":"Musselwhite","avatar":"https://robohash.org/fugitvelofficiis.jpg?size=50x50&set=set1"},
{"id":51,"first_name":"Felecia","last_name":"Stonham","avatar":"https://robohash.org/rationesequiesse.png?size=50x50&set=set1"},
{"id":52,"first_name":"Marchelle","last_name":"Mearing","avatar":"https://robohash.org/dolorconsequaturea.bmp?size=50x50&set=set1"},
{"id":53,"first_name":"El","last_name":"Griffen","avatar":"https://robohash.org/temporeblanditiisquo.png?size=50x50&set=set1"},
{"id":54,"first_name":"Remus","last_name":"Sesons","avatar":"https://robohash.org/doloremearumet.png?size=50x50&set=set1"},
{"id":55,"first_name":"Glynnis","last_name":"Loweth","avatar":"https://robohash.org/aliasnecessitatibusasperiores.png?size=50x50&set=set1"},
{"id":56,"first_name":"Wilton","last_name":"Sauvain","avatar":"https://robohash.org/aliquidquaedelectus.png?size=50x50&set=set1"},
{"id":57,"first_name":"Aridatha","last_name":"Nellen","avatar":"https://robohash.org/quoscorrupticumque.bmp?size=50x50&set=set1"},
{"id":58,"first_name":"Judd","last_name":"Sheehan","avatar":"https://robohash.org/hicquiaexcepturi.bmp?size=50x50&set=set1"},
{"id":59,"first_name":"Menard","last_name":"Plenty","avatar":"https://robohash.org/quidemeostempora.png?size=50x50&set=set1"},
{"id":60,"first_name":"Tracee","last_name":"Morden","avatar":"https://robohash.org/recusandaeconsequaturblanditiis.bmp?size=50x50&set=set1"},
{"id":61,"first_name":"Veronica","last_name":"Hyder","avatar":"https://robohash.org/solutaillonon.jpg?size=50x50&set=set1"},
{"id":62,"first_name":"Harmon","last_name":"Rawson","avatar":"https://robohash.org/cumquevoluptateset.png?size=50x50&set=set1"},
{"id":63,"first_name":"Marnie","last_name":"Drees","avatar":"https://robohash.org/dictaadperferendis.bmp?size=50x50&set=set1"},
{"id":64,"first_name":"Kailey","last_name":"Chevis","avatar":"https://robohash.org/adipiscilaborumullam.bmp?size=50x50&set=set1"},
{"id":65,"first_name":"Gray","last_name":"Bettleson","avatar":"https://robohash.org/eligendiquisaut.bmp?size=50x50&set=set1"},
{"id":66,"first_name":"Bernardine","last_name":"Boult","avatar":"https://robohash.org/expeditaetnulla.png?size=50x50&set=set1"},
{"id":67,"first_name":"Fae","last_name":"Rodriguez","avatar":"https://robohash.org/omnisteneturest.jpg?size=50x50&set=set1"},
{"id":68,"first_name":"Ariel","last_name":"Sherme","avatar":"https://robohash.org/nonculpased.png?size=50x50&set=set1"},
{"id":69,"first_name":"Nicko","last_name":"Dankersley","avatar":"https://robohash.org/delectusiureminima.jpg?size=50x50&set=set1"},
{"id":70,"first_name":"Renato","last_name":"Camble","avatar":"https://robohash.org/odioquodet.jpg?size=50x50&set=set1"},
{"id":71,"first_name":"Lazarus","last_name":"Timbridge","avatar":"https://robohash.org/repellendussitquod.png?size=50x50&set=set1"},
{"id":72,"first_name":"Tracie","last_name":"Golightly","avatar":"https://robohash.org/quaeratsitenim.jpg?size=50x50&set=set1"},
{"id":73,"first_name":"Cally","last_name":"Legg","avatar":"https://robohash.org/cumquiomnis.jpg?size=50x50&set=set1"},
{"id":74,"first_name":"Wakefield","last_name":"Heinsius","avatar":"https://robohash.org/suscipitnonfacilis.png?size=50x50&set=set1"},
{"id":75,"first_name":"Harri","last_name":"Skym","avatar":"https://robohash.org/iureblanditiisquae.jpg?size=50x50&set=set1"},
{"id":76,"first_name":"Meg","last_name":"Doughtery","avatar":"https://robohash.org/enimfugaid.png?size=50x50&set=set1"},
{"id":77,"first_name":"Ailey","last_name":"Mallon","avatar":"https://robohash.org/sedautfacilis.png?size=50x50&set=set1"},
{"id":78,"first_name":"Lyn","last_name":"Snasdell","avatar":"https://robohash.org/etdelenitiexpedita.png?size=50x50&set=set1"},
{"id":79,"first_name":"Dame","last_name":"Burfield","avatar":"https://robohash.org/laudantiuminventoreexpedita.png?size=50x50&set=set1"},
{"id":80,"first_name":"Dom","last_name":"Greenhead","avatar":"https://robohash.org/inciduntquidemcumque.png?size=50x50&set=set1"},
{"id":81,"first_name":"Tanya","last_name":"Ennor","avatar":"https://robohash.org/totamquianihil.png?size=50x50&set=set1"},
{"id":82,"first_name":"Marylinda","last_name":"Essam","avatar":"https://robohash.org/eumprovidentin.bmp?size=50x50&set=set1"},
{"id":83,"first_name":"Conrad","last_name":"De Caroli","avatar":"https://robohash.org/sitaspernaturnemo.bmp?size=50x50&set=set1"},
{"id":84,"first_name":"Meredeth","last_name":"Forrest","avatar":"https://robohash.org/cumidexpedita.bmp?size=50x50&set=set1"},
{"id":85,"first_name":"Chantal","last_name":"Rickardsson","avatar":"https://robohash.org/laborumofficiarerum.jpg?size=50x50&set=set1"},
{"id":86,"first_name":"Mina","last_name":"Josephsen","avatar":"https://robohash.org/nullaquiipsam.jpg?size=50x50&set=set1"},
{"id":87,"first_name":"Krishnah","last_name":"Leopard","avatar":"https://robohash.org/rationelaborumvel.png?size=50x50&set=set1"},
{"id":88,"first_name":"Madison","last_name":"Scottesmoor","avatar":"https://robohash.org/atnumquamplaceat.bmp?size=50x50&set=set1"},
{"id":89,"first_name":"Lindsy","last_name":"Clingan","avatar":"https://robohash.org/eumeta.bmp?size=50x50&set=set1"},
{"id":90,"first_name":"Mal","last_name":"July","avatar":"https://robohash.org/rerumutet.jpg?size=50x50&set=set1"},
{"id":91,"first_name":"Magdalen","last_name":"Jansen","avatar":"https://robohash.org/quiremsapiente.bmp?size=50x50&set=set1"},
{"id":92,"first_name":"Whitman","last_name":"Kinastan","avatar":"https://robohash.org/nonsuntet.jpg?size=50x50&set=set1"},
{"id":93,"first_name":"Cyb","last_name":"Margetson","avatar":"https://robohash.org/repellendusdoloreut.jpg?size=50x50&set=set1"},
{"id":94,"first_name":"Tiebout","last_name":"Akehurst","avatar":"https://robohash.org/voluptatesquoautem.bmp?size=50x50&set=set1"},
{"id":95,"first_name":"Serena","last_name":"Timmins","avatar":"https://robohash.org/quidemvelitquia.png?size=50x50&set=set1"},
{"id":96,"first_name":"Winn","last_name":"Cape","avatar":"https://robohash.org/autemcorruptinihil.jpg?size=50x50&set=set1"},
{"id":97,"first_name":"Hale","last_name":"Gonnard","avatar":"https://robohash.org/idofficiasaepe.bmp?size=50x50&set=set1"},
{"id":98,"first_name":"Shane","last_name":"Tredgold","avatar":"https://robohash.org/nonquosperferendis.png?size=50x50&set=set1"},
{"id":99,"first_name":"Merle","last_name":"D' Angelo","avatar":"https://robohash.org/fugavitaeaspernatur.png?size=50x50&set=set1"},
{"id":100,"first_name":"Parke","last_name":"Blaisdale","avatar":"https://robohash.org/atsuscipitaliquam.png?size=50x50&set=set1"},
{"id":101,"first_name":"Morgan","last_name":"Lenin","avatar":"https://robohash.org/etdignissimosqui.jpg?size=50x50&set=set1"},
{"id":102,"first_name":"Hazlett","last_name":"Delacourt","avatar":"https://robohash.org/similiquetemporequia.bmp?size=50x50&set=set1"},
{"id":103,"first_name":"Nolana","last_name":"Drakeford","avatar":"https://robohash.org/sedinet.jpg?size=50x50&set=set1"},
{"id":104,"first_name":"Pacorro","last_name":"Stairmand","avatar":"https://robohash.org/laborummodiiure.bmp?size=50x50&set=set1"},
{"id":105,"first_name":"Sunshine","last_name":"Bainton","avatar":"https://robohash.org/ametlaudantiumfugit.jpg?size=50x50&set=set1"},
{"id":106,"first_name":"Fidelity","last_name":"Poyser","avatar":"https://robohash.org/voluptatesnonaut.bmp?size=50x50&set=set1"},
{"id":107,"first_name":"Kahlil","last_name":"Youde","avatar":"https://robohash.org/voluptatemexcepturinihil.jpg?size=50x50&set=set1"},
{"id":108,"first_name":"Abba","last_name":"Rockliffe","avatar":"https://robohash.org/voluptatemvitaerecusandae.bmp?size=50x50&set=set1"},
{"id":109,"first_name":"Shadow","last_name":"Quipp","avatar":"https://robohash.org/quaeautsint.png?size=50x50&set=set1"},
{"id":110,"first_name":"Coop","last_name":"Whisson","avatar":"https://robohash.org/quisquambeataequia.jpg?size=50x50&set=set1"},
{"id":111,"first_name":"Addia","last_name":"Mc Queen","avatar":"https://robohash.org/corruptivoluptatumsit.jpg?size=50x50&set=set1"},
{"id":112,"first_name":"Joshua","last_name":"Pawlicki","avatar":"https://robohash.org/nemoveniamunde.jpg?size=50x50&set=set1"},
{"id":113,"first_name":"Ced","last_name":"Morehall","avatar":"https://robohash.org/iurerepudiandaenisi.png?size=50x50&set=set1"},
{"id":114,"first_name":"Catherine","last_name":"Prujean","avatar":"https://robohash.org/dolorumrempariatur.jpg?size=50x50&set=set1"},
{"id":115,"first_name":"Corina","last_name":"Bolle","avatar":"https://robohash.org/autofficiissit.jpg?size=50x50&set=set1"},
{"id":116,"first_name":"Milzie","last_name":"Bezemer","avatar":"https://robohash.org/quoculparem.png?size=50x50&set=set1"},
{"id":117,"first_name":"Hillary","last_name":"Kristoffersson","avatar":"https://robohash.org/voluptasquossunt.bmp?size=50x50&set=set1"},
{"id":118,"first_name":"Gearalt","last_name":"Mowsley","avatar":"https://robohash.org/ipsumquiconsequatur.png?size=50x50&set=set1"},
{"id":119,"first_name":"Nadia","last_name":"Haddinton","avatar":"https://robohash.org/deseruntomnisaccusamus.png?size=50x50&set=set1"},
{"id":120,"first_name":"Andreana","last_name":"Greensite","avatar":"https://robohash.org/quisofficiamolestiae.png?size=50x50&set=set1"},
{"id":121,"first_name":"Amabel","last_name":"Bour","avatar":"https://robohash.org/molestiasnullaut.jpg?size=50x50&set=set1"},
{"id":122,"first_name":"Hesther","last_name":"Jocelyn","avatar":"https://robohash.org/doloremoditnon.bmp?size=50x50&set=set1"},
{"id":123,"first_name":"Lefty","last_name":"Charrier","avatar":"https://robohash.org/eumutsequi.bmp?size=50x50&set=set1"},
{"id":124,"first_name":"Aurel","last_name":"Tailour","avatar":"https://robohash.org/omnisrecusandaetemporibus.bmp?size=50x50&set=set1"},
{"id":125,"first_name":"Kata","last_name":"Britcher","avatar":"https://robohash.org/porrooditet.jpg?size=50x50&set=set1"},
{"id":126,"first_name":"Emelia","last_name":"Downage","avatar":"https://robohash.org/utomnisconsequatur.bmp?size=50x50&set=set1"},
{"id":127,"first_name":"Glen","last_name":"Coneybeer","avatar":"https://robohash.org/remuteaque.png?size=50x50&set=set1"},
{"id":128,"first_name":"Stafford","last_name":"Shoobridge","avatar":"https://robohash.org/veritatiseiusnon.png?size=50x50&set=set1"},
{"id":129,"first_name":"Bee","last_name":"Tibbles","avatar":"https://robohash.org/nihilutreprehenderit.bmp?size=50x50&set=set1"},
{"id":130,"first_name":"Velvet","last_name":"Beynke","avatar":"https://robohash.org/quiaetperferendis.png?size=50x50&set=set1"},
{"id":131,"first_name":"Karlotta","last_name":"Siegertsz","avatar":"https://robohash.org/laborumsintexpedita.jpg?size=50x50&set=set1"},
{"id":132,"first_name":"Leoline","last_name":"Scholte","avatar":"https://robohash.org/fugiatevenietdicta.jpg?size=50x50&set=set1"},
{"id":133,"first_name":"Kellen","last_name":"Sebire","avatar":"https://robohash.org/quaeoccaecatinecessitatibus.png?size=50x50&set=set1"},
{"id":134,"first_name":"Emelina","last_name":"Munt","avatar":"https://robohash.org/quiutea.bmp?size=50x50&set=set1"},
{"id":135,"first_name":"Lucita","last_name":"Sarch","avatar":"https://robohash.org/rationeeligendiquidem.png?size=50x50&set=set1"},
{"id":136,"first_name":"Brnaba","last_name":"Crowcum","avatar":"https://robohash.org/evenietautdolor.jpg?size=50x50&set=set1"},
{"id":137,"first_name":"Griffie","last_name":"Rableau","avatar":"https://robohash.org/aperiamdelenitiet.jpg?size=50x50&set=set1"},
{"id":138,"first_name":"Phylys","last_name":"Arnould","avatar":"https://robohash.org/evenietquifugiat.png?size=50x50&set=set1"},
{"id":139,"first_name":"Melodee","last_name":"Nehls","avatar":"https://robohash.org/quascommodised.bmp?size=50x50&set=set1"},
{"id":140,"first_name":"Lolly","last_name":"Pridham","avatar":"https://robohash.org/estisteearum.bmp?size=50x50&set=set1"},
{"id":141,"first_name":"Ferdinanda","last_name":"Sussems","avatar":"https://robohash.org/exillumsint.jpg?size=50x50&set=set1"},
{"id":142,"first_name":"Lorinda","last_name":"Hayer","avatar":"https://robohash.org/enimanimiaspernatur.bmp?size=50x50&set=set1"},
{"id":143,"first_name":"Susanetta","last_name":"Ledbury","avatar":"https://robohash.org/cumvoluptatemipsam.png?size=50x50&set=set1"},
{"id":144,"first_name":"Vale","last_name":"Landsbury","avatar":"https://robohash.org/ataccusamusneque.png?size=50x50&set=set1"},
{"id":145,"first_name":"Stephana","last_name":"Sibly","avatar":"https://robohash.org/magnivelitet.jpg?size=50x50&set=set1"},
{"id":146,"first_name":"Gusta","last_name":"Whaymand","avatar":"https://robohash.org/voluptateexercitationemexcepturi.bmp?size=50x50&set=set1"},
{"id":147,"first_name":"Robby","last_name":"Sclater","avatar":"https://robohash.org/autemcumqui.bmp?size=50x50&set=set1"},
{"id":148,"first_name":"Gabbie","last_name":"Selbach","avatar":"https://robohash.org/accusamusatquequi.bmp?size=50x50&set=set1"},
{"id":149,"first_name":"Brett","last_name":"McMeekan","avatar":"https://robohash.org/pariaturdistinctioeius.bmp?size=50x50&set=set1"},
{"id":150,"first_name":"Tod","last_name":"Redmire","avatar":"https://robohash.org/eafacilisoccaecati.png?size=50x50&set=set1"},
{"id":151,"first_name":"Starlene","last_name":"Brittan","avatar":"https://robohash.org/omnisconsequaturad.bmp?size=50x50&set=set1"},
{"id":152,"first_name":"Noach","last_name":"Danilewicz","avatar":"https://robohash.org/reprehenderitpossimuscorporis.bmp?size=50x50&set=set1"},
{"id":153,"first_name":"Ilario","last_name":"Sidnell","avatar":"https://robohash.org/utrerumrerum.png?size=50x50&set=set1"},
{"id":154,"first_name":"Yettie","last_name":"Butland","avatar":"https://robohash.org/etlaboriosamcumque.png?size=50x50&set=set1"},
{"id":155,"first_name":"Eunice","last_name":"Saffle","avatar":"https://robohash.org/fugiatrerumin.png?size=50x50&set=set1"},
{"id":156,"first_name":"Vicky","last_name":"Hulburt","avatar":"https://robohash.org/molestiaeesseblanditiis.bmp?size=50x50&set=set1"},
{"id":157,"first_name":"Carmon","last_name":"Abbis","avatar":"https://robohash.org/nihilquiet.bmp?size=50x50&set=set1"},
{"id":158,"first_name":"Onida","last_name":"McFaell","avatar":"https://robohash.org/esttemporibusfacere.png?size=50x50&set=set1"},
{"id":159,"first_name":"Florie","last_name":"Phillins","avatar":"https://robohash.org/recusandaefugasint.jpg?size=50x50&set=set1"},
{"id":160,"first_name":"Lia","last_name":"Conant","avatar":"https://robohash.org/etvoluptatemexercitationem.jpg?size=50x50&set=set1"},
{"id":161,"first_name":"Billy","last_name":"De Giovanni","avatar":"https://robohash.org/ipsaexplicaboquisquam.bmp?size=50x50&set=set1"},
{"id":162,"first_name":"Cammy","last_name":"Laterza","avatar":"https://robohash.org/corruptivoluptatesed.png?size=50x50&set=set1"},
{"id":163,"first_name":"Nestor","last_name":"Popescu","avatar":"https://robohash.org/delenitiautrepudiandae.png?size=50x50&set=set1"},
{"id":164,"first_name":"Alexandra","last_name":"Mottershead","avatar":"https://robohash.org/possimustemporibusratione.bmp?size=50x50&set=set1"},
{"id":165,"first_name":"Sam","last_name":"Sawley","avatar":"https://robohash.org/utasperioresdebitis.jpg?size=50x50&set=set1"},
{"id":166,"first_name":"Gary","last_name":"Kingsbury","avatar":"https://robohash.org/velitdolorvitae.png?size=50x50&set=set1"},
{"id":167,"first_name":"Zoe","last_name":"Carless","avatar":"https://robohash.org/quaedoloresdeleniti.bmp?size=50x50&set=set1"},
{"id":168,"first_name":"Kilian","last_name":"Barnfield","avatar":"https://robohash.org/temporibusvelitcum.png?size=50x50&set=set1"},
{"id":169,"first_name":"Tuckie","last_name":"Aldrick","avatar":"https://robohash.org/quiblanditiisnihil.png?size=50x50&set=set1"},
{"id":170,"first_name":"Yolane","last_name":"Cooper","avatar":"https://robohash.org/nostrumenimut.png?size=50x50&set=set1"},
{"id":171,"first_name":"Ahmed","last_name":"Heppenspall","avatar":"https://robohash.org/eaetquasi.jpg?size=50x50&set=set1"},
{"id":172,"first_name":"Annalee","last_name":"Clutton","avatar":"https://robohash.org/odioculpamolestias.png?size=50x50&set=set1"},
{"id":173,"first_name":"Nara","last_name":"Aguilar","avatar":"https://robohash.org/reiciendisundeeum.png?size=50x50&set=set1"},
{"id":174,"first_name":"Chantalle","last_name":"Linger","avatar":"https://robohash.org/delenitiremvelit.jpg?size=50x50&set=set1"},
{"id":175,"first_name":"Orland","last_name":"Brasse","avatar":"https://robohash.org/numquamquisalias.png?size=50x50&set=set1"},
{"id":176,"first_name":"Gavin","last_name":"Jendas","avatar":"https://robohash.org/consequaturreiciendisin.jpg?size=50x50&set=set1"},
{"id":177,"first_name":"Dorian","last_name":"Blucher","avatar":"https://robohash.org/quitemporaquaerat.jpg?size=50x50&set=set1"},
{"id":178,"first_name":"Constantina","last_name":"Esmonde","avatar":"https://robohash.org/molestiaecommodiet.jpg?size=50x50&set=set1"},
{"id":179,"first_name":"Amalie","last_name":"Rymill","avatar":"https://robohash.org/reprehenderitdignissimosquia.png?size=50x50&set=set1"},
{"id":180,"first_name":"Danya","last_name":"Meineken","avatar":"https://robohash.org/laboriosamverovelit.jpg?size=50x50&set=set1"},
{"id":181,"first_name":"Chelsy","last_name":"Glaysher","avatar":"https://robohash.org/repudiandaeenimquis.jpg?size=50x50&set=set1"},
{"id":182,"first_name":"Ursula","last_name":"Hunnywell","avatar":"https://robohash.org/avoluptatumaut.png?size=50x50&set=set1"},
{"id":183,"first_name":"Sayer","last_name":"Baudin","avatar":"https://robohash.org/nostrumrecusandaeunde.jpg?size=50x50&set=set1"},
{"id":184,"first_name":"Margaretta","last_name":"Scarman","avatar":"https://robohash.org/oditseditaque.bmp?size=50x50&set=set1"},
{"id":185,"first_name":"Cynthia","last_name":"Gadsby","avatar":"https://robohash.org/asperioresatquedicta.bmp?size=50x50&set=set1"},
{"id":186,"first_name":"Daveen","last_name":"De Santos","avatar":"https://robohash.org/quoenimet.jpg?size=50x50&set=set1"},
{"id":187,"first_name":"Roxana","last_name":"Owbrick","avatar":"https://robohash.org/sitrecusandaeprovident.bmp?size=50x50&set=set1"},
{"id":188,"first_name":"Violante","last_name":"Messier","avatar":"https://robohash.org/molestiaeducimusin.png?size=50x50&set=set1"},
{"id":189,"first_name":"Lorelle","last_name":"Beaconsall","avatar":"https://robohash.org/etdolorcommodi.bmp?size=50x50&set=set1"},
{"id":190,"first_name":"Kissie","last_name":"Kineton","avatar":"https://robohash.org/nihilquasfacilis.png?size=50x50&set=set1"},
{"id":191,"first_name":"Donaugh","last_name":"Kimberley","avatar":"https://robohash.org/accusantiumeuminventore.jpg?size=50x50&set=set1"},
{"id":192,"first_name":"Bevan","last_name":"Murray","avatar":"https://robohash.org/voluptatemnecessitatibusest.png?size=50x50&set=set1"},
{"id":193,"first_name":"Ric","last_name":"Malamore","avatar":"https://robohash.org/voluptatibusfaceremolestiae.png?size=50x50&set=set1"},
{"id":194,"first_name":"Estrellita","last_name":"Dunkerley","avatar":"https://robohash.org/eumautat.jpg?size=50x50&set=set1"},
{"id":195,"first_name":"Karol","last_name":"Molnar","avatar":"https://robohash.org/aliquiddoloremut.bmp?size=50x50&set=set1"},
{"id":196,"first_name":"Hadleigh","last_name":"Breslau","avatar":"https://robohash.org/quiadelectusconsequatur.jpg?size=50x50&set=set1"},
{"id":197,"first_name":"Kitty","last_name":"Tuxill","avatar":"https://robohash.org/evenietaccusantiumsoluta.png?size=50x50&set=set1"},
{"id":198,"first_name":"Panchito","last_name":"Tersay","avatar":"https://robohash.org/vitaevoluptatemea.png?size=50x50&set=set1"},
{"id":199,"first_name":"Jonie","last_name":"Clearley","avatar":"https://robohash.org/oditenimimpedit.jpg?size=50x50&set=set1"},
{"id":200,"first_name":"Delmar","last_name":"Wiggans","avatar":"https://robohash.org/quiapariaturvoluptas.png?size=50x50&set=set1"},
{"id":201,"first_name":"Gaby","last_name":"Flag","avatar":"https://robohash.org/ettemporeimpedit.jpg?size=50x50&set=set1"},
{"id":202,"first_name":"Marrissa","last_name":"O' Bee","avatar":"https://robohash.org/doloresexercitationemaspernatur.png?size=50x50&set=set1"},
{"id":203,"first_name":"Drusilla","last_name":"Sydney","avatar":"https://robohash.org/omnisquaealiquam.jpg?size=50x50&set=set1"},
{"id":204,"first_name":"Marie-ann","last_name":"Eglise","avatar":"https://robohash.org/minusiureaut.png?size=50x50&set=set1"},
{"id":205,"first_name":"Piggy","last_name":"Concannon","avatar":"https://robohash.org/etsintvoluptas.bmp?size=50x50&set=set1"},
{"id":206,"first_name":"Anders","last_name":"Dailey","avatar":"https://robohash.org/nequequaseaque.jpg?size=50x50&set=set1"},
{"id":207,"first_name":"Dwight","last_name":"Petrichat","avatar":"https://robohash.org/nonmollitiasuscipit.png?size=50x50&set=set1"},
{"id":208,"first_name":"Emera","last_name":"Sowerbutts","avatar":"https://robohash.org/nihillaboriosamaspernatur.png?size=50x50&set=set1"},
{"id":209,"first_name":"Sayre","last_name":"Dagleas","avatar":"https://robohash.org/facilisrepudiandaequia.jpg?size=50x50&set=set1"},
{"id":210,"first_name":"Gun","last_name":"Cumpsty","avatar":"https://robohash.org/fugitassumendaet.jpg?size=50x50&set=set1"},
{"id":211,"first_name":"Malinde","last_name":"Cotesford","avatar":"https://robohash.org/undeconsequaturdelectus.png?size=50x50&set=set1"},
{"id":212,"first_name":"Codie","last_name":"Makepeace","avatar":"https://robohash.org/minuscommodivelit.png?size=50x50&set=set1"},
{"id":213,"first_name":"Darnall","last_name":"Pierrepoint","avatar":"https://robohash.org/quibusdamvoluptatesaliquid.bmp?size=50x50&set=set1"},
{"id":214,"first_name":"Annabel","last_name":"Tyson","avatar":"https://robohash.org/eiusbeataetenetur.png?size=50x50&set=set1"},
{"id":215,"first_name":"Kippie","last_name":"Scoines","avatar":"https://robohash.org/quodquiharum.png?size=50x50&set=set1"},
{"id":216,"first_name":"Felice","last_name":"Cockren","avatar":"https://robohash.org/beataeearumsunt.jpg?size=50x50&set=set1"},
{"id":217,"first_name":"Eziechiele","last_name":"Mac Geaney","avatar":"https://robohash.org/laboriosamnonut.png?size=50x50&set=set1"},
{"id":218,"first_name":"Tomas","last_name":"Gainor","avatar":"https://robohash.org/etvoluptasex.png?size=50x50&set=set1"},
{"id":219,"first_name":"Fanya","last_name":"Gallen","avatar":"https://robohash.org/ipsumearumdelectus.png?size=50x50&set=set1"},
{"id":220,"first_name":"Richy","last_name":"Titman","avatar":"https://robohash.org/teneturprovidentin.bmp?size=50x50&set=set1"},
{"id":221,"first_name":"Ronni","last_name":"Gathercoal","avatar":"https://robohash.org/eaqueeumsed.png?size=50x50&set=set1"},
{"id":222,"first_name":"Nanny","last_name":"Austick","avatar":"https://robohash.org/esseplaceatmodi.bmp?size=50x50&set=set1"},
{"id":223,"first_name":"Kali","last_name":"Lubman","avatar":"https://robohash.org/nonveniamaut.bmp?size=50x50&set=set1"},
{"id":224,"first_name":"Maryanna","last_name":"Halpin","avatar":"https://robohash.org/nihilsittenetur.bmp?size=50x50&set=set1"},
{"id":225,"first_name":"Ninnetta","last_name":"Maypole","avatar":"https://robohash.org/exreiciendisdolorem.bmp?size=50x50&set=set1"},
{"id":226,"first_name":"Thor","last_name":"MacKomb","avatar":"https://robohash.org/quimaximemolestias.png?size=50x50&set=set1"},
{"id":227,"first_name":"Gerti","last_name":"Pollard","avatar":"https://robohash.org/aliquiddoloribusblanditiis.png?size=50x50&set=set1"},
{"id":228,"first_name":"Mordecai","last_name":"Mapledorum","avatar":"https://robohash.org/fugiatillumautem.jpg?size=50x50&set=set1"},
{"id":229,"first_name":"Hyacinth","last_name":"Kilgour","avatar":"https://robohash.org/perferendisexplicaboerror.jpg?size=50x50&set=set1"},
{"id":230,"first_name":"Val","last_name":"Witcher","avatar":"https://robohash.org/mollitiaveniamtotam.bmp?size=50x50&set=set1"},
{"id":231,"first_name":"Kirstyn","last_name":"Casarino","avatar":"https://robohash.org/quiaasperioresexplicabo.jpg?size=50x50&set=set1"},
{"id":232,"first_name":"Nerte","last_name":"Semrad","avatar":"https://robohash.org/sedetpraesentium.bmp?size=50x50&set=set1"},
{"id":233,"first_name":"Aguste","last_name":"Ickowicz","avatar":"https://robohash.org/quiaabillo.bmp?size=50x50&set=set1"},
{"id":234,"first_name":"Mendel","last_name":"Welbeck","avatar":"https://robohash.org/mollitiaquaerataperiam.jpg?size=50x50&set=set1"},
{"id":235,"first_name":"Cindi","last_name":"Taft","avatar":"https://robohash.org/deseruntsuntveritatis.jpg?size=50x50&set=set1"},
{"id":236,"first_name":"Addison","last_name":"Coopland","avatar":"https://robohash.org/quiaexmodi.bmp?size=50x50&set=set1"},
{"id":237,"first_name":"Nicholas","last_name":"Barthelmes","avatar":"https://robohash.org/voluptatibusrecusandaeimpedit.jpg?size=50x50&set=set1"},
{"id":238,"first_name":"Ellerey","last_name":"Illston","avatar":"https://robohash.org/quibusdamminimasimilique.bmp?size=50x50&set=set1"},
{"id":239,"first_name":"Suzie","last_name":"Dagless","avatar":"https://robohash.org/namexercitationemmolestiae.bmp?size=50x50&set=set1"},
{"id":240,"first_name":"Breena","last_name":"Cann","avatar":"https://robohash.org/essenonnemo.bmp?size=50x50&set=set1"},
{"id":241,"first_name":"Sylvester","last_name":"Philipsson","avatar":"https://robohash.org/doloremqueetharum.png?size=50x50&set=set1"},
{"id":242,"first_name":"Dode","last_name":"Lammerich","avatar":"https://robohash.org/voluptatibusetvero.jpg?size=50x50&set=set1"},
{"id":243,"first_name":"Ichabod","last_name":"Iacovo","avatar":"https://robohash.org/explicaboquisquamaut.jpg?size=50x50&set=set1"},
{"id":244,"first_name":"Lenna","last_name":"Lonnon","avatar":"https://robohash.org/uteumquis.jpg?size=50x50&set=set1"},
{"id":245,"first_name":"Dannie","last_name":"Barstock","avatar":"https://robohash.org/quiautvoluptas.bmp?size=50x50&set=set1"},
{"id":246,"first_name":"Clarine","last_name":"Belsey","avatar":"https://robohash.org/aliasodioest.jpg?size=50x50&set=set1"},
{"id":247,"first_name":"Bibby","last_name":"Outram","avatar":"https://robohash.org/molestiaenihilneque.jpg?size=50x50&set=set1"},
{"id":248,"first_name":"Bonny","last_name":"Elham","avatar":"https://robohash.org/animicumquequia.jpg?size=50x50&set=set1"},
{"id":249,"first_name":"Jordon","last_name":"Foggarty","avatar":"https://robohash.org/nequererumsed.jpg?size=50x50&set=set1"},
{"id":250,"first_name":"Jordon","last_name":"Hustings","avatar":"https://robohash.org/oditomnisexpedita.jpg?size=50x50&set=set1"},
{"id":251,"first_name":"Windy","last_name":"Tuttiett","avatar":"https://robohash.org/nostrumperspiciatisqui.jpg?size=50x50&set=set1"},
{"id":252,"first_name":"Cathrine","last_name":"Skeldon","avatar":"https://robohash.org/excepturiquiasuscipit.bmp?size=50x50&set=set1"},
{"id":253,"first_name":"Cyrille","last_name":"McCrystal","avatar":"https://robohash.org/laborumsolutaat.png?size=50x50&set=set1"},
{"id":254,"first_name":"Vlad","last_name":"Kingdon","avatar":"https://robohash.org/eaidut.jpg?size=50x50&set=set1"},
{"id":255,"first_name":"Lynea","last_name":"Gason","avatar":"https://robohash.org/voluptasatvoluptatem.png?size=50x50&set=set1"},
{"id":256,"first_name":"Nial","last_name":"Horley","avatar":"https://robohash.org/veroestminus.jpg?size=50x50&set=set1"},
{"id":257,"first_name":"Christine","last_name":"Edwardson","avatar":"https://robohash.org/reprehenderitveritatisdicta.jpg?size=50x50&set=set1"},
{"id":258,"first_name":"Jase","last_name":"Sandyford","avatar":"https://robohash.org/hictemporamaiores.png?size=50x50&set=set1"},
{"id":259,"first_name":"Alwyn","last_name":"Plumbridge","avatar":"https://robohash.org/quirecusandaeut.bmp?size=50x50&set=set1"},
{"id":260,"first_name":"Maggie","last_name":"Zavattari","avatar":"https://robohash.org/aperiameligendifuga.png?size=50x50&set=set1"},
{"id":261,"first_name":"Roderich","last_name":"Stinchcombe","avatar":"https://robohash.org/quiautdolor.png?size=50x50&set=set1"},
{"id":262,"first_name":"Oliy","last_name":"Tours","avatar":"https://robohash.org/estsimiliquesaepe.bmp?size=50x50&set=set1"},
{"id":263,"first_name":"Jeffy","last_name":"Beagles","avatar":"https://robohash.org/minimacorruptiullam.jpg?size=50x50&set=set1"},
{"id":264,"first_name":"Kassie","last_name":"Ivakhno","avatar":"https://robohash.org/namquibusdamfugit.jpg?size=50x50&set=set1"},
{"id":265,"first_name":"Kial","last_name":"Meech","avatar":"https://robohash.org/omnisdoloresconsectetur.bmp?size=50x50&set=set1"},
{"id":266,"first_name":"Matthiew","last_name":"Ilieve","avatar":"https://robohash.org/aperiamaliquamdicta.png?size=50x50&set=set1"},
{"id":267,"first_name":"Stesha","last_name":"Eayres","avatar":"https://robohash.org/autemaspernaturvelit.bmp?size=50x50&set=set1"},
{"id":268,"first_name":"Drew","last_name":"Barrell","avatar":"https://robohash.org/seddoloramet.png?size=50x50&set=set1"},
{"id":269,"first_name":"Melly","last_name":"Di Nisco","avatar":"https://robohash.org/sedquasdolorum.png?size=50x50&set=set1"},
{"id":270,"first_name":"Ferguson","last_name":"Drohun","avatar":"https://robohash.org/nisiatitaque.png?size=50x50&set=set1"},
{"id":271,"first_name":"Brendon","last_name":"Slocombe","avatar":"https://robohash.org/similiqueliberoa.jpg?size=50x50&set=set1"},
{"id":272,"first_name":"Delmer","last_name":"Ewenson","avatar":"https://robohash.org/inciduntomnisnihil.jpg?size=50x50&set=set1"},
{"id":273,"first_name":"Tallie","last_name":"Schulter","avatar":"https://robohash.org/ullamrepellendusvoluptatum.bmp?size=50x50&set=set1"},
{"id":274,"first_name":"Maxy","last_name":"Vasilischev","avatar":"https://robohash.org/impeditvelitullam.jpg?size=50x50&set=set1"},
{"id":275,"first_name":"Jeremias","last_name":"Siehard","avatar":"https://robohash.org/omnisdoloresnisi.png?size=50x50&set=set1"},
{"id":276,"first_name":"Humfried","last_name":"Verdy","avatar":"https://robohash.org/cumquisquae.bmp?size=50x50&set=set1"},
{"id":277,"first_name":"Fancy","last_name":"Hardwell","avatar":"https://robohash.org/voluptatibusdistinctiosint.png?size=50x50&set=set1"},
{"id":278,"first_name":"Gav","last_name":"Suddick","avatar":"https://robohash.org/velitvoluptatumvero.bmp?size=50x50&set=set1"},
{"id":279,"first_name":"Lorinda","last_name":"Bogey","avatar":"https://robohash.org/pariatureiusa.bmp?size=50x50&set=set1"},
{"id":280,"first_name":"Cooper","last_name":"Chessil","avatar":"https://robohash.org/animiutconsequuntur.jpg?size=50x50&set=set1"},
{"id":281,"first_name":"Benetta","last_name":"Harcus","avatar":"https://robohash.org/architectoevenietdolores.jpg?size=50x50&set=set1"},
{"id":282,"first_name":"Erwin","last_name":"Soane","avatar":"https://robohash.org/magnamenimeos.png?size=50x50&set=set1"},
{"id":283,"first_name":"Philip","last_name":"Swyer-Sexey","avatar":"https://robohash.org/rerumvoluptatemmolestias.png?size=50x50&set=set1"},
{"id":284,"first_name":"Ronnica","last_name":"Ranklin","avatar":"https://robohash.org/numquamquasquaerat.png?size=50x50&set=set1"},
{"id":285,"first_name":"Ginnie","last_name":"Solly","avatar":"https://robohash.org/quiaeaquemaxime.png?size=50x50&set=set1"},
{"id":286,"first_name":"Morganne","last_name":"Newlove","avatar":"https://robohash.org/liberosedblanditiis.bmp?size=50x50&set=set1"},
{"id":287,"first_name":"Sandy","last_name":"Ashford","avatar":"https://robohash.org/utvitaebeatae.bmp?size=50x50&set=set1"},
{"id":288,"first_name":"Mamie","last_name":"Hedman","avatar":"https://robohash.org/quaseiusdelectus.jpg?size=50x50&set=set1"},
{"id":289,"first_name":"Brocky","last_name":"Anespie","avatar":"https://robohash.org/modieoset.bmp?size=50x50&set=set1"},
{"id":290,"first_name":"Katherine","last_name":"Wingar","avatar":"https://robohash.org/pariaturquismollitia.jpg?size=50x50&set=set1"},
{"id":291,"first_name":"Niles","last_name":"Coplestone","avatar":"https://robohash.org/molestiaedistinctioillum.jpg?size=50x50&set=set1"},
{"id":292,"first_name":"Marv","last_name":"Eloi","avatar":"https://robohash.org/doloremqueutautem.jpg?size=50x50&set=set1"},
{"id":293,"first_name":"Cynthea","last_name":"Pibsworth","avatar":"https://robohash.org/estipsamcorrupti.png?size=50x50&set=set1"},
{"id":294,"first_name":"Rickey","last_name":"Banbrick","avatar":"https://robohash.org/perspiciatisducimusreiciendis.bmp?size=50x50&set=set1"},
{"id":295,"first_name":"Gilberte","last_name":"Championnet","avatar":"https://robohash.org/esttemporasimilique.jpg?size=50x50&set=set1"},
{"id":296,"first_name":"Annelise","last_name":"Doel","avatar":"https://robohash.org/quiquibusdamnon.png?size=50x50&set=set1"},
{"id":297,"first_name":"Bonnibelle","last_name":"Neesam","avatar":"https://robohash.org/officiisnumquamvoluptatem.bmp?size=50x50&set=set1"},
{"id":298,"first_name":"Patrizia","last_name":"Helbeck","avatar":"https://robohash.org/quiaestsapiente.bmp?size=50x50&set=set1"},
{"id":299,"first_name":"Mellisent","last_name":"Rosgen","avatar":"https://robohash.org/cupiditatedistinctiosaepe.png?size=50x50&set=set1"},
{"id":300,"first_name":"Rodi","last_name":"Argabrite","avatar":"https://robohash.org/consequaturutvoluptatem.bmp?size=50x50&set=set1"},
{"id":301,"first_name":"Marissa","last_name":"Marieton","avatar":"https://robohash.org/remfacilisexpedita.bmp?size=50x50&set=set1"},
{"id":302,"first_name":"Lettie","last_name":"Naisbitt","avatar":"https://robohash.org/abnecessitatibusesse.png?size=50x50&set=set1"},
{"id":303,"first_name":"Arv","last_name":"Margrett","avatar":"https://robohash.org/molestiasliberolaudantium.png?size=50x50&set=set1"},
{"id":304,"first_name":"Joelie","last_name":"Drakes","avatar":"https://robohash.org/sitrepudiandaevoluptatem.png?size=50x50&set=set1"},
{"id":305,"first_name":"Loren","last_name":"Nicklin","avatar":"https://robohash.org/repellatundelaudantium.bmp?size=50x50&set=set1"},
{"id":306,"first_name":"Madison","last_name":"Randlesome","avatar":"https://robohash.org/quirepudiandaeomnis.bmp?size=50x50&set=set1"},
{"id":307,"first_name":"Eileen","last_name":"Grinnikov","avatar":"https://robohash.org/estporrobeatae.bmp?size=50x50&set=set1"},
{"id":308,"first_name":"Tine","last_name":"Doppler","avatar":"https://robohash.org/delenitisitet.bmp?size=50x50&set=set1"},
{"id":309,"first_name":"Edgard","last_name":"Sokill","avatar":"https://robohash.org/perferendisrationeamet.bmp?size=50x50&set=set1"},
{"id":310,"first_name":"Kara-lynn","last_name":"Spalls","avatar":"https://robohash.org/inventorenostrumquaerat.jpg?size=50x50&set=set1"},
{"id":311,"first_name":"Lyndell","last_name":"Soppett","avatar":"https://robohash.org/illumvoluptatumtempora.bmp?size=50x50&set=set1"},
{"id":312,"first_name":"Vanny","last_name":"Kenna","avatar":"https://robohash.org/dignissimosnostrumanimi.jpg?size=50x50&set=set1"},
{"id":313,"first_name":"Lyn","last_name":"Brenston","avatar":"https://robohash.org/minimasedquo.jpg?size=50x50&set=set1"},
{"id":314,"first_name":"Fremont","last_name":"Hazeldene","avatar":"https://robohash.org/inciduntquiatque.bmp?size=50x50&set=set1"},
{"id":315,"first_name":"Melantha","last_name":"Enbury","avatar":"https://robohash.org/illoquisunt.png?size=50x50&set=set1"},
{"id":316,"first_name":"Gordon","last_name":"Hallford","avatar":"https://robohash.org/quamquoid.jpg?size=50x50&set=set1"},
{"id":317,"first_name":"Joey","last_name":"Debenham","avatar":"https://robohash.org/eaessesimilique.bmp?size=50x50&set=set1"},
{"id":318,"first_name":"Maurice","last_name":"Alyutin","avatar":"https://robohash.org/etetquo.jpg?size=50x50&set=set1"},
{"id":319,"first_name":"Robinia","last_name":"Tudball","avatar":"https://robohash.org/saepeatquerecusandae.png?size=50x50&set=set1"},
{"id":320,"first_name":"Sissy","last_name":"Castiblanco","avatar":"https://robohash.org/quiquiaat.bmp?size=50x50&set=set1"},
{"id":321,"first_name":"Dede","last_name":"Chapple","avatar":"https://robohash.org/etnatusquia.bmp?size=50x50&set=set1"},
{"id":322,"first_name":"Foss","last_name":"Gypps","avatar":"https://robohash.org/nemoplaceatvoluptatem.png?size=50x50&set=set1"},
{"id":323,"first_name":"Hanny","last_name":"Scarff","avatar":"https://robohash.org/temporaestvoluptas.jpg?size=50x50&set=set1"},
{"id":324,"first_name":"Shane","last_name":"Fleetwood","avatar":"https://robohash.org/sedtemporequod.bmp?size=50x50&set=set1"},
{"id":325,"first_name":"Kim","last_name":"Holmyard","avatar":"https://robohash.org/explicaboeavel.bmp?size=50x50&set=set1"},
{"id":326,"first_name":"Elmo","last_name":"Cripps","avatar":"https://robohash.org/ipsaveritatisrepellat.bmp?size=50x50&set=set1"},
{"id":327,"first_name":"Rowen","last_name":"Mityushkin","avatar":"https://robohash.org/eaqueprovidentmagnam.bmp?size=50x50&set=set1"},
{"id":328,"first_name":"Dulcie","last_name":"Orriss","avatar":"https://robohash.org/molestiaesequieaque.bmp?size=50x50&set=set1"},
{"id":329,"first_name":"Blane","last_name":"Dalmon","avatar":"https://robohash.org/doloresimpeditenim.jpg?size=50x50&set=set1"},
{"id":330,"first_name":"Jesse","last_name":"Beevens","avatar":"https://robohash.org/omnisconsequaturenim.bmp?size=50x50&set=set1"},
{"id":331,"first_name":"Darla","last_name":"Hudd","avatar":"https://robohash.org/velenimlaboriosam.jpg?size=50x50&set=set1"},
{"id":332,"first_name":"Camey","last_name":"Mulvin","avatar":"https://robohash.org/occaecatitemporibusaut.jpg?size=50x50&set=set1"},
{"id":333,"first_name":"Bob","last_name":"Eary","avatar":"https://robohash.org/doloremautcum.png?size=50x50&set=set1"},
{"id":334,"first_name":"Carmelle","last_name":"Crapper","avatar":"https://robohash.org/vitaenonesse.bmp?size=50x50&set=set1"},
{"id":335,"first_name":"Ophelia","last_name":"Charnock","avatar":"https://robohash.org/eosdeleniticonsequuntur.bmp?size=50x50&set=set1"},
{"id":336,"first_name":"Isidora","last_name":"Shoebridge","avatar":"https://robohash.org/omnisdoloremsint.bmp?size=50x50&set=set1"},
{"id":337,"first_name":"Raimundo","last_name":"Crane","avatar":"https://robohash.org/harumfugiatsint.png?size=50x50&set=set1"},
{"id":338,"first_name":"Dimitri","last_name":"Duker","avatar":"https://robohash.org/modiofficiarepudiandae.png?size=50x50&set=set1"},
{"id":339,"first_name":"Gregorius","last_name":"Mumford","avatar":"https://robohash.org/rerumetaut.png?size=50x50&set=set1"},
{"id":340,"first_name":"Lia","last_name":"Fellgett","avatar":"https://robohash.org/veldolorumearum.bmp?size=50x50&set=set1"},
{"id":341,"first_name":"Elga","last_name":"Schinetti","avatar":"https://robohash.org/estdoloressit.png?size=50x50&set=set1"},
{"id":342,"first_name":"Gay","last_name":"Covelle","avatar":"https://robohash.org/laudantiumsuntducimus.jpg?size=50x50&set=set1"},
{"id":343,"first_name":"Oriana","last_name":"Speare","avatar":"https://robohash.org/optioquinon.png?size=50x50&set=set1"},
{"id":344,"first_name":"Caritta","last_name":"Dalliwater","avatar":"https://robohash.org/voluptassintreprehenderit.jpg?size=50x50&set=set1"},
{"id":345,"first_name":"Cristie","last_name":"Manhare","avatar":"https://robohash.org/excepturifugittempora.jpg?size=50x50&set=set1"},
{"id":346,"first_name":"Cindy","last_name":"Reardon","avatar":"https://robohash.org/illumetvelit.png?size=50x50&set=set1"},
{"id":347,"first_name":"Malinde","last_name":"Savege","avatar":"https://robohash.org/inquiqui.png?size=50x50&set=set1"},
{"id":348,"first_name":"Aldrich","last_name":"Hatley","avatar":"https://robohash.org/autemnamipsum.png?size=50x50&set=set1"},
{"id":349,"first_name":"Walt","last_name":"Balogh","avatar":"https://robohash.org/inventoreesselaboriosam.bmp?size=50x50&set=set1"},
{"id":350,"first_name":"Anastassia","last_name":"Mosley","avatar":"https://robohash.org/suscipitfaceredolor.bmp?size=50x50&set=set1"},
{"id":351,"first_name":"Una","last_name":"Lomen","avatar":"https://robohash.org/nihilomniseligendi.jpg?size=50x50&set=set1"},
{"id":352,"first_name":"Berna","last_name":"Michurin","avatar":"https://robohash.org/omnisetrerum.jpg?size=50x50&set=set1"},
{"id":353,"first_name":"Andy","last_name":"Cary","avatar":"https://robohash.org/estlaboreveritatis.jpg?size=50x50&set=set1"},
{"id":354,"first_name":"Beryl","last_name":"Santori","avatar":"https://robohash.org/isteanostrum.png?size=50x50&set=set1"},
{"id":355,"first_name":"Costanza","last_name":"Corran","avatar":"https://robohash.org/nesciuntullamut.jpg?size=50x50&set=set1"},
{"id":356,"first_name":"Bern","last_name":"Elcum","avatar":"https://robohash.org/utquassit.bmp?size=50x50&set=set1"},
{"id":357,"first_name":"Allyn","last_name":"Nichols","avatar":"https://robohash.org/iustosaepemodi.png?size=50x50&set=set1"},
{"id":358,"first_name":"Tris","last_name":"D'Enrico","avatar":"https://robohash.org/ametsimiliqueut.png?size=50x50&set=set1"},
{"id":359,"first_name":"Caye","last_name":"Franzotto","avatar":"https://robohash.org/omnismolestiaeipsam.png?size=50x50&set=set1"},
{"id":360,"first_name":"Stesha","last_name":"Gibbin","avatar":"https://robohash.org/enimveldelectus.jpg?size=50x50&set=set1"},
{"id":361,"first_name":"Rurik","last_name":"Paxman","avatar":"https://robohash.org/culpaeaqueea.bmp?size=50x50&set=set1"},
{"id":362,"first_name":"Giustino","last_name":"Tadlow","avatar":"https://robohash.org/namsaepequasi.bmp?size=50x50&set=set1"},
{"id":363,"first_name":"Kalila","last_name":"Gammill","avatar":"https://robohash.org/voluptatesanimiipsam.png?size=50x50&set=set1"},
{"id":364,"first_name":"Brucie","last_name":"Dadley","avatar":"https://robohash.org/necessitatibusdoloribuset.png?size=50x50&set=set1"},
{"id":365,"first_name":"Teddie","last_name":"MacQuarrie","avatar":"https://robohash.org/expeditaautblanditiis.bmp?size=50x50&set=set1"},
{"id":366,"first_name":"Burtie","last_name":"Jefferies","avatar":"https://robohash.org/facereestfugit.jpg?size=50x50&set=set1"},
{"id":367,"first_name":"Maritsa","last_name":"Chalkly","avatar":"https://robohash.org/rerumliberoofficiis.png?size=50x50&set=set1"},
{"id":368,"first_name":"Tansy","last_name":"Caldecott","avatar":"https://robohash.org/innullaillum.jpg?size=50x50&set=set1"},
{"id":369,"first_name":"Elnora","last_name":"Agron","avatar":"https://robohash.org/etnobisvoluptates.png?size=50x50&set=set1"},
{"id":370,"first_name":"Tommy","last_name":"Akker","avatar":"https://robohash.org/ipsumnullabeatae.bmp?size=50x50&set=set1"},
{"id":371,"first_name":"Hyacinthie","last_name":"Hadfield","avatar":"https://robohash.org/laborumcorruptivoluptas.png?size=50x50&set=set1"},
{"id":372,"first_name":"Quentin","last_name":"Cayford","avatar":"https://robohash.org/modideseruntitaque.png?size=50x50&set=set1"},
{"id":373,"first_name":"Eartha","last_name":"Casseldine","avatar":"https://robohash.org/teneturnemoquaerat.bmp?size=50x50&set=set1"},
{"id":374,"first_name":"Sallie","last_name":"Rodinger","avatar":"https://robohash.org/eossintut.bmp?size=50x50&set=set1"},
{"id":375,"first_name":"Max","last_name":"Galilee","avatar":"https://robohash.org/etomnisdignissimos.png?size=50x50&set=set1"},
{"id":376,"first_name":"Evelina","last_name":"Jarville","avatar":"https://robohash.org/doloribussuscipitratione.png?size=50x50&set=set1"},
{"id":377,"first_name":"Demetris","last_name":"Placidi","avatar":"https://robohash.org/distinctioisteaccusamus.png?size=50x50&set=set1"},
{"id":378,"first_name":"Dom","last_name":"Lennarde","avatar":"https://robohash.org/hicipsamodi.jpg?size=50x50&set=set1"},
{"id":379,"first_name":"Brander","last_name":"Kitchenside","avatar":"https://robohash.org/voluptasadipiscirepellendus.bmp?size=50x50&set=set1"},
{"id":380,"first_name":"Laurianne","last_name":"O'Cannavan","avatar":"https://robohash.org/nequeetsimilique.jpg?size=50x50&set=set1"},
{"id":381,"first_name":"Casie","last_name":"Grigorushkin","avatar":"https://robohash.org/sedreruminventore.bmp?size=50x50&set=set1"},
{"id":382,"first_name":"Alphard","last_name":"Bence","avatar":"https://robohash.org/nemoessecupiditate.jpg?size=50x50&set=set1"},
{"id":383,"first_name":"Adolph","last_name":"Gammet","avatar":"https://robohash.org/nonmodiquasi.bmp?size=50x50&set=set1"},
{"id":384,"first_name":"Laurens","last_name":"Inggall","avatar":"https://robohash.org/consequatursimiliqueautem.jpg?size=50x50&set=set1"},
{"id":385,"first_name":"Harlan","last_name":"Noorwood","avatar":"https://robohash.org/dignissimoserrordolor.jpg?size=50x50&set=set1"},
{"id":386,"first_name":"Ase","last_name":"Checklin","avatar":"https://robohash.org/consequunturdoloremqueoccaecati.png?size=50x50&set=set1"},
{"id":387,"first_name":"Ariel","last_name":"Shepherdson","avatar":"https://robohash.org/facilisestest.jpg?size=50x50&set=set1"},
{"id":388,"first_name":"Emmey","last_name":"Barstowk","avatar":"https://robohash.org/molestiaeutdolorem.png?size=50x50&set=set1"},
{"id":389,"first_name":"Lotte","last_name":"Marquot","avatar":"https://robohash.org/etlaudantiumsit.png?size=50x50&set=set1"},
{"id":390,"first_name":"Julian","last_name":"Odeson","avatar":"https://robohash.org/autemasunt.bmp?size=50x50&set=set1"},
{"id":391,"first_name":"Kathryne","last_name":"Lincke","avatar":"https://robohash.org/officiisoptioincidunt.bmp?size=50x50&set=set1"},
{"id":392,"first_name":"Elaina","last_name":"Timmins","avatar":"https://robohash.org/eadistinctiotemporibus.jpg?size=50x50&set=set1"},
{"id":393,"first_name":"Melitta","last_name":"Fernihough","avatar":"https://robohash.org/minimaautquis.bmp?size=50x50&set=set1"},
{"id":394,"first_name":"Barnebas","last_name":"Ullyott","avatar":"https://robohash.org/laudantiumsuscipitmolestias.jpg?size=50x50&set=set1"},
{"id":395,"first_name":"Eileen","last_name":"Bayfield","avatar":"https://robohash.org/expeditasaepenesciunt.png?size=50x50&set=set1"},
{"id":396,"first_name":"Ede","last_name":"Maddin","avatar":"https://robohash.org/sitreprehenderitunde.bmp?size=50x50&set=set1"},
{"id":397,"first_name":"Fremont","last_name":"Greggersen","avatar":"https://robohash.org/veropariaturdebitis.jpg?size=50x50&set=set1"},
{"id":398,"first_name":"Abey","last_name":"Pesek","avatar":"https://robohash.org/incidunteaquisquam.png?size=50x50&set=set1"},
{"id":399,"first_name":"Kay","last_name":"Briers","avatar":"https://robohash.org/asperioresremat.png?size=50x50&set=set1"},
{"id":400,"first_name":"Edmund","last_name":"Newcombe","avatar":"https://robohash.org/quosettenetur.jpg?size=50x50&set=set1"},
{"id":401,"first_name":"Cristiano","last_name":"Le Pruvost","avatar":"https://robohash.org/inciduntvitaeeos.bmp?size=50x50&set=set1"},
{"id":402,"first_name":"Jarret","last_name":"McKinty","avatar":"https://robohash.org/abeataeaspernatur.png?size=50x50&set=set1"},
{"id":403,"first_name":"Wynny","last_name":"Cordingly","avatar":"https://robohash.org/porroveniamomnis.bmp?size=50x50&set=set1"},
{"id":404,"first_name":"Say","last_name":"MacAnulty","avatar":"https://robohash.org/eoslaboriosamculpa.bmp?size=50x50&set=set1"},
{"id":405,"first_name":"Wilbert","last_name":"Rooksby","avatar":"https://robohash.org/eosoptiodoloribus.jpg?size=50x50&set=set1"},
{"id":406,"first_name":"Iona","last_name":"Jonson","avatar":"https://robohash.org/assumendalaborumnobis.png?size=50x50&set=set1"},
{"id":407,"first_name":"Linnet","last_name":"Bertrand","avatar":"https://robohash.org/doloreperferendisquia.jpg?size=50x50&set=set1"},
{"id":408,"first_name":"Jillie","last_name":"Abreheart","avatar":"https://robohash.org/eaquibusdamet.png?size=50x50&set=set1"},
{"id":409,"first_name":"Itch","last_name":"Hammell","avatar":"https://robohash.org/verovoluptatumlabore.png?size=50x50&set=set1"},
{"id":410,"first_name":"Shawn","last_name":"Jackman","avatar":"https://robohash.org/veldoloremvel.png?size=50x50&set=set1"},
{"id":411,"first_name":"Feodor","last_name":"Wethered","avatar":"https://robohash.org/nullavitaeid.jpg?size=50x50&set=set1"},
{"id":412,"first_name":"Ogdon","last_name":"Naulls","avatar":"https://robohash.org/aestsimilique.bmp?size=50x50&set=set1"},
{"id":413,"first_name":"Jaquenette","last_name":"Mapston","avatar":"https://robohash.org/estquiaomnis.bmp?size=50x50&set=set1"},
{"id":414,"first_name":"Lorine","last_name":"Deane","avatar":"https://robohash.org/ducimusetconsequuntur.png?size=50x50&set=set1"},
{"id":415,"first_name":"Lucio","last_name":"Binne","avatar":"https://robohash.org/saepebeataenatus.jpg?size=50x50&set=set1"},
{"id":416,"first_name":"Collete","last_name":"Prester","avatar":"https://robohash.org/doloribusarchitectosit.jpg?size=50x50&set=set1"},
{"id":417,"first_name":"Olly","last_name":"Bothen","avatar":"https://robohash.org/ipsumlaudantiumnatus.bmp?size=50x50&set=set1"},
{"id":418,"first_name":"Sancho","last_name":"Brecken","avatar":"https://robohash.org/adlaboreaut.bmp?size=50x50&set=set1"},
{"id":419,"first_name":"Maddy","last_name":"Valadez","avatar":"https://robohash.org/saepeipsaat.bmp?size=50x50&set=set1"},
{"id":420,"first_name":"Barney","last_name":"Sherrocks","avatar":"https://robohash.org/rerumodiorem.bmp?size=50x50&set=set1"},
{"id":421,"first_name":"Raphael","last_name":"Grouvel","avatar":"https://robohash.org/iureatquesed.jpg?size=50x50&set=set1"},
{"id":422,"first_name":"Trina","last_name":"Frawley","avatar":"https://robohash.org/cupiditatelaboreest.png?size=50x50&set=set1"},
{"id":423,"first_name":"Hugo","last_name":"O'Leahy","avatar":"https://robohash.org/eoscommodiconsequatur.jpg?size=50x50&set=set1"},
{"id":424,"first_name":"Karrie","last_name":"Tawse","avatar":"https://robohash.org/iurerationequia.png?size=50x50&set=set1"},
{"id":425,"first_name":"Emyle","last_name":"Marquese","avatar":"https://robohash.org/reprehenderitminimadolorem.bmp?size=50x50&set=set1"},
{"id":426,"first_name":"Marcel","last_name":"Banbury","avatar":"https://robohash.org/ipsumatquecommodi.jpg?size=50x50&set=set1"},
{"id":427,"first_name":"Dannie","last_name":"Birchill","avatar":"https://robohash.org/estinventoresequi.jpg?size=50x50&set=set1"},
{"id":428,"first_name":"Minda","last_name":"Ody","avatar":"https://robohash.org/laboriosamcumquedelectus.bmp?size=50x50&set=set1"},
{"id":429,"first_name":"Leonerd","last_name":"Rustich","avatar":"https://robohash.org/suscipitquidemut.jpg?size=50x50&set=set1"},
{"id":430,"first_name":"Bartholemy","last_name":"Freyn","avatar":"https://robohash.org/exercitationemquasmaiores.jpg?size=50x50&set=set1"},
{"id":431,"first_name":"Wilbert","last_name":"Skough","avatar":"https://robohash.org/repellenduspossimusdolore.bmp?size=50x50&set=set1"},
{"id":432,"first_name":"Brad","last_name":"Just","avatar":"https://robohash.org/natusquialabore.png?size=50x50&set=set1"},
{"id":433,"first_name":"Renate","last_name":"Wildash","avatar":"https://robohash.org/doloremqueautemblanditiis.jpg?size=50x50&set=set1"},
{"id":434,"first_name":"Theressa","last_name":"Stivani","avatar":"https://robohash.org/consequaturdoloremrerum.bmp?size=50x50&set=set1"},
{"id":435,"first_name":"Reggis","last_name":"Silly","avatar":"https://robohash.org/deseruntducimusaut.bmp?size=50x50&set=set1"},
{"id":436,"first_name":"Garner","last_name":"Inkpin","avatar":"https://robohash.org/nihiletpariatur.jpg?size=50x50&set=set1"},
{"id":437,"first_name":"Pearce","last_name":"Bitchener","avatar":"https://robohash.org/cumqueessevero.png?size=50x50&set=set1"},
{"id":438,"first_name":"Pet","last_name":"Novakovic","avatar":"https://robohash.org/optionihilullam.bmp?size=50x50&set=set1"},
{"id":439,"first_name":"Nataniel","last_name":"Hutson","avatar":"https://robohash.org/iureasperioresconsequatur.bmp?size=50x50&set=set1"},
{"id":440,"first_name":"Kevyn","last_name":"Brouwer","avatar":"https://robohash.org/doloresoditid.jpg?size=50x50&set=set1"},
{"id":441,"first_name":"Sunshine","last_name":"Covey","avatar":"https://robohash.org/teneturconsequaturdolores.png?size=50x50&set=set1"},
{"id":442,"first_name":"Wolfgang","last_name":"Galle","avatar":"https://robohash.org/nemoreprehenderitducimus.jpg?size=50x50&set=set1"},
{"id":443,"first_name":"Starr","last_name":"Bunn","avatar":"https://robohash.org/iustoconsequunturprovident.jpg?size=50x50&set=set1"},
{"id":444,"first_name":"Emory","last_name":"Izzat","avatar":"https://robohash.org/enimdoloribusquibusdam.png?size=50x50&set=set1"},
{"id":445,"first_name":"Annabell","last_name":"Longman","avatar":"https://robohash.org/odioillumex.jpg?size=50x50&set=set1"},
{"id":446,"first_name":"Stacee","last_name":"Allenson","avatar":"https://robohash.org/dignissimossintnecessitatibus.jpg?size=50x50&set=set1"},
{"id":447,"first_name":"Abagael","last_name":"Neaves","avatar":"https://robohash.org/fugiatquisaccusamus.bmp?size=50x50&set=set1"},
{"id":448,"first_name":"Xenia","last_name":"Dyble","avatar":"https://robohash.org/teneturoccaecaticumque.jpg?size=50x50&set=set1"},
{"id":449,"first_name":"Lilyan","last_name":"Senecaut","avatar":"https://robohash.org/officiaquolibero.jpg?size=50x50&set=set1"},
{"id":450,"first_name":"Lana","last_name":"Bratt","avatar":"https://robohash.org/omnismaximevoluptas.jpg?size=50x50&set=set1"},
{"id":451,"first_name":"Franky","last_name":"Obey","avatar":"https://robohash.org/minimaetquas.jpg?size=50x50&set=set1"},
{"id":452,"first_name":"Glory","last_name":"Luparti","avatar":"https://robohash.org/odioaccusamusquia.bmp?size=50x50&set=set1"},
{"id":453,"first_name":"Laurie","last_name":"Redgrove","avatar":"https://robohash.org/etrepellatreprehenderit.png?size=50x50&set=set1"},
{"id":454,"first_name":"Cort","last_name":"Rennolds","avatar":"https://robohash.org/quasiadipisciab.png?size=50x50&set=set1"},
{"id":455,"first_name":"Bridgette","last_name":"Kemble","avatar":"https://robohash.org/laboriosamremea.bmp?size=50x50&set=set1"},
{"id":456,"first_name":"Hilarius","last_name":"Mioni","avatar":"https://robohash.org/itaqueetvoluptas.jpg?size=50x50&set=set1"},
{"id":457,"first_name":"Mycah","last_name":"Elion","avatar":"https://robohash.org/doloremistequi.png?size=50x50&set=set1"},
{"id":458,"first_name":"Olivier","last_name":"Sodeau","avatar":"https://robohash.org/voluptateaspernaturut.bmp?size=50x50&set=set1"},
{"id":459,"first_name":"Base","last_name":"Allpress","avatar":"https://robohash.org/autdignissimosut.png?size=50x50&set=set1"},
{"id":460,"first_name":"Vladimir","last_name":"Cundict","avatar":"https://robohash.org/nihilfugitvoluptatem.jpg?size=50x50&set=set1"},
{"id":461,"first_name":"Alfredo","last_name":"Matthias","avatar":"https://robohash.org/optionihilrepellat.jpg?size=50x50&set=set1"},
{"id":462,"first_name":"Colman","last_name":"Noar","avatar":"https://robohash.org/voluptatibustotamperferendis.bmp?size=50x50&set=set1"},
{"id":463,"first_name":"Rriocard","last_name":"Wohler","avatar":"https://robohash.org/consecteturdolorimpedit.jpg?size=50x50&set=set1"},
{"id":464,"first_name":"Valeria","last_name":"Francisco","avatar":"https://robohash.org/consequaturevenietexcepturi.bmp?size=50x50&set=set1"},
{"id":465,"first_name":"Cathee","last_name":"Boulter","avatar":"https://robohash.org/laudantiumdoloret.jpg?size=50x50&set=set1"},
{"id":466,"first_name":"Isa","last_name":"Clamp","avatar":"https://robohash.org/harumsuscipitrem.jpg?size=50x50&set=set1"},
{"id":467,"first_name":"Janenna","last_name":"Librey","avatar":"https://robohash.org/delenitiquidemfugit.jpg?size=50x50&set=set1"},
{"id":468,"first_name":"Kristyn","last_name":"Dedman","avatar":"https://robohash.org/saepeaccusantiumexcepturi.jpg?size=50x50&set=set1"},
{"id":469,"first_name":"Delilah","last_name":"Spooner","avatar":"https://robohash.org/dictainporro.png?size=50x50&set=set1"},
{"id":470,"first_name":"Fraze","last_name":"Sheardown","avatar":"https://robohash.org/repellendusasperioresmolestiae.bmp?size=50x50&set=set1"},
{"id":471,"first_name":"Willy","last_name":"Longstaff","avatar":"https://robohash.org/nisidignissimosquos.jpg?size=50x50&set=set1"},
{"id":472,"first_name":"Ondrea","last_name":"Seston","avatar":"https://robohash.org/repudiandaequosrerum.jpg?size=50x50&set=set1"},
{"id":473,"first_name":"Nicolle","last_name":"Goude","avatar":"https://robohash.org/corporisfugiteligendi.png?size=50x50&set=set1"},
{"id":474,"first_name":"Angelo","last_name":"Joyce","avatar":"https://robohash.org/etremut.jpg?size=50x50&set=set1"},
{"id":475,"first_name":"Sari","last_name":"Scardefield","avatar":"https://robohash.org/maioresdeseruntdignissimos.bmp?size=50x50&set=set1"},
{"id":476,"first_name":"Eberhard","last_name":"Goddert.sf","avatar":"https://robohash.org/necessitatibusmollitiaaccusamus.jpg?size=50x50&set=set1"},
{"id":477,"first_name":"Dorelia","last_name":"McDarmid","avatar":"https://robohash.org/quodrerumnihil.jpg?size=50x50&set=set1"},
{"id":478,"first_name":"Mel","last_name":"Sly","avatar":"https://robohash.org/quaeratcumdolorem.bmp?size=50x50&set=set1"},
{"id":479,"first_name":"Marietta","last_name":"Pudney","avatar":"https://robohash.org/utvelsed.png?size=50x50&set=set1"},
{"id":480,"first_name":"Livia","last_name":"Mulqueen","avatar":"https://robohash.org/etveldeleniti.bmp?size=50x50&set=set1"},
{"id":481,"first_name":"Kristin","last_name":"Frostick","avatar":"https://robohash.org/officiavoluptatemerror.bmp?size=50x50&set=set1"},
{"id":482,"first_name":"Mignonne","last_name":"Grim","avatar":"https://robohash.org/nonipsamofficiis.jpg?size=50x50&set=set1"},
{"id":483,"first_name":"Melany","last_name":"Petronis","avatar":"https://robohash.org/quiaetquis.png?size=50x50&set=set1"},
{"id":484,"first_name":"Katleen","last_name":"Basford","avatar":"https://robohash.org/quasietquas.jpg?size=50x50&set=set1"},
{"id":485,"first_name":"Peyton","last_name":"Scardefield","avatar":"https://robohash.org/nostrumatsed.bmp?size=50x50&set=set1"},
{"id":486,"first_name":"Tammy","last_name":"Verbrugge","avatar":"https://robohash.org/eaqueeiusvelit.png?size=50x50&set=set1"},
{"id":487,"first_name":"Nevins","last_name":"Bernardeau","avatar":"https://robohash.org/nihilestdistinctio.bmp?size=50x50&set=set1"},
{"id":488,"first_name":"Rollins","last_name":"Dautry","avatar":"https://robohash.org/architectohicipsam.bmp?size=50x50&set=set1"},
{"id":489,"first_name":"Ailey","last_name":"Haquin","avatar":"https://robohash.org/aliquamrerumcupiditate.png?size=50x50&set=set1"},
{"id":490,"first_name":"Kissie","last_name":"Morriss","avatar":"https://robohash.org/quisquamestmodi.jpg?size=50x50&set=set1"},
{"id":491,"first_name":"Fleming","last_name":"Gabler","avatar":"https://robohash.org/optioharumsapiente.jpg?size=50x50&set=set1"},
{"id":492,"first_name":"Johannes","last_name":"Wheldon","avatar":"https://robohash.org/ipsamquiamet.png?size=50x50&set=set1"},
{"id":493,"first_name":"Helene","last_name":"Hull","avatar":"https://robohash.org/asperioresdeseruntqui.bmp?size=50x50&set=set1"},
{"id":494,"first_name":"Blisse","last_name":"Dummigan","avatar":"https://robohash.org/quibusdamfacilisrepellat.bmp?size=50x50&set=set1"},
{"id":495,"first_name":"Gabbi","last_name":"Doull","avatar":"https://robohash.org/etquasivero.png?size=50x50&set=set1"},
{"id":496,"first_name":"Nerita","last_name":"Tregale","avatar":"https://robohash.org/repudiandaeenimplaceat.jpg?size=50x50&set=set1"},
{"id":497,"first_name":"Barnett","last_name":"Thompson","avatar":"https://robohash.org/quoveroipsum.jpg?size=50x50&set=set1"},
{"id":498,"first_name":"Vivia","last_name":"Brockherst","avatar":"https://robohash.org/recusandaefugitut.jpg?size=50x50&set=set1"},
{"id":499,"first_name":"Joshia","last_name":"Jagels","avatar":"https://robohash.org/fugaestea.bmp?size=50x50&set=set1"},
{"id":500,"first_name":"Lyle","last_name":"Shutt","avatar":"https://robohash.org/adomnisdolor.png?size=50x50&set=set1"}]